cli.py
engine.py
nodes/__init__.py
nodes/common/__init__.py
nodes/common/call_llm_node.py
nodes/common/fetch_files.py
nodes/common/fetch_files_node.py
nodes/common/files_to_prompt_node.py
nodes/common/get_files_node.py
nodes/common/parse_code_node.py
nodes/common/save_snapshot_node.py
nodes/common/snapshot_files_node.py
nodes/common/write_file_node.py
nodes/common/diff/__init__.py
nodes/common/diff/get_git_diff_node.py
nodes/common/diff/parse_diff_node.py
nodes/common/review/__init__.py
nodes/common/review/aggregate_findings_node.py
nodes/common/review/performance_review_node.py
nodes/common/review/quality_review_node.py
nodes/common/review/security_review_node.py
nodes/custom/__init__.py
nodes/custom/check_naming_convention_node.py
nodes/tutorial/__init__.py
nodes/tutorial/tutorial_nodes.py
nodes/tutorial/tutorial_nodes_temp.py
outcomeforge-0.1.2.data/data/prompts/arch_drift.prompt.md
outcomeforge-0.1.2.data/data/prompts/rag_query.prompt.md
outcomeforge-0.1.2.data/data/prompts/regression.prompt.md
outcomeforge-0.1.2.data/data/prompts/repo_adapt.prompt.md
outcomeforge-0.1.2.data/data/prompts/snapshot.prompt.md
scenarios/__init__.py
scenarios/scenario_1_local_snapshot.py
scenarios/scenario_2_repo_adapt.py
scenarios/scenario_3_regression.py
scenarios/scenario_4_arch_drift.py
scenarios/scenario_5_local_rag.py
scenarios/scenario_6_code_review.py
scenarios/scenario_7_codebase_tutorial.py
utils/__init__.py
utils/ast_parser.py
utils/crawl_github_files.py
utils/crawl_local_files.py
utils/llm_client.py
utils/naming_checker.py
utils/plan_executor.py
utils/state_manager.py
utils/token_counter.py
outcomeforge-0.1.2.dist-info/METADATA
outcomeforge-0.1.2.dist-info/WHEEL
outcomeforge-0.1.2.dist-info/entry_points.txt
outcomeforge-0.1.2.dist-info/top_level.txt
outcomeforge-0.1.2.dist-info/RECORD
