Metadata-Version: 2.4
Name: outcomeforge
Version: 0.1.2
Summary: A modular framework to forge and verify intelligent outcomes
Home-page: https://github.com/yourusername/outcomeforge
Author: outcomeForge Team
License-Expression: MIT
Project-URL: Homepage, https://github.com/yourusername/outcomeforge
Project-URL: Documentation, https://github.com/yourusername/outcomeforge#readme
Project-URL: Repository, https://github.com/yourusername/outcomeforge
Project-URL: Issues, https://github.com/yourusername/outcomeforge/issues
Keywords: code-analysis,llm,ai,devops,quality-assurance
Classifier: Development Status :: 3 - Alpha
Classifier: Intended Audience :: Developers
Classifier: Topic :: Software Development :: Quality Assurance
Classifier: Topic :: Software Development :: Libraries :: Application Frameworks
Classifier: Programming Language :: Python :: 3
Classifier: Programming Language :: Python :: 3.7
Classifier: Programming Language :: Python :: 3.8
Classifier: Programming Language :: Python :: 3.9
Classifier: Programming Language :: Python :: 3.10
Classifier: Programming Language :: Python :: 3.11
Requires-Python: >=3.7
Requires-Dist: click>=8.0.0
Requires-Dist: pyyaml>=6.0.0
Requires-Dist: requests>=2.28.0
Requires-Dist: gitpython>=3.1.0
Requires-Dist: tree-sitter>=0.20.0
Requires-Dist: jinja2>=3.1.0
Requires-Dist: anthropic>=0.18.0
Requires-Dist: openai>=1.0.0
Requires-Dist: tiktoken>=0.5.0
Provides-Extra: dev
Requires-Dist: pytest>=7.0.0; extra == "dev"
Requires-Dist: pytest-cov>=4.0.0; extra == "dev"
Dynamic: home-page
Dynamic: requires-python
